[{"name":"sql.active_record","payload":{"sql":"SELECT  \"users\".* FROM \"users\" WHERE \"users\".\"id\" = ?  ORDER BY \"users\".\"id\" ASC LIMIT 1","name":"User Load","connection_id":70132700731080,"statement_name":null,"binds":[[{"name":"id","cast_type":{"precision":null,"scale":null,"limit":null,"range":"-2147483648...2147483648"},"sql_type":"INTEGER","null":false,"default":null,"default_function":null},2]],"line":28,"filename":"/Users/mikechen/oracle/jointest/app/controllers/orders_controller.rb","method":"checkout_allpay"},"time":"2015-08-30T00:17:21.280+08:00","transaction_id":"4228ffae4b393754db8c","end":"2015-08-30T00:17:21.281+08:00","children":[],"duration":0.501},{"name":"sql.active_record","payload":{"sql":"SELECT  \"orders\".* FROM \"orders\" WHERE \"orders\".\"user_id\" = ? AND \"orders\".\"id\" = ? LIMIT 1","name":"Order Load","connection_id":70132700731080,"statement_name":null,"binds":[[{"name":"user_id","cast_type":{"precision":null,"scale":null,"limit":4,"range":"-2147483648...2147483648"},"sql_type":"integer(4)","null":true,"default":null,"default_function":null},2],[{"name":"id","cast_type":{"precision":null,"scale":null,"limit":null,"range":"-2147483648...2147483648"},"sql_type":"INTEGER","null":false,"default":null,"default_function":null},25]],"line":28,"filename":"/Users/mikechen/oracle/jointest/app/controllers/orders_controller.rb","method":"checkout_allpay"},"time":"2015-08-30T00:17:21.286+08:00","transaction_id":"4228ffae4b393754db8c","end":"2015-08-30T00:17:21.286+08:00","children":[],"duration":0.864},{"name":"sql.active_record","payload":{"sql":"PRAGMA table_info(\"payments\")","name":"SCHEMA","connection_id":70132700731080,"statement_name":null,"binds":[],"line":30,"filename":"/Users/mikechen/oracle/jointest/app/controllers/orders_controller.rb","method":"checkout_allpay"},"time":"2015-08-30T00:17:21.295+08:00","transaction_id":"4228ffae4b393754db8c","end":"2015-08-30T00:17:21.295+08:00","children":[],"duration":0.27099999999999996},{"name":"sql.active_record","payload":{"sql":"PRAGMA table_info(\"payments\")","name":"SCHEMA","connection_id":70132700731080,"statement_name":null,"binds":[],"line":30,"filename":"/Users/mikechen/oracle/jointest/app/controllers/orders_controller.rb","method":"checkout_allpay"},"time":"2015-08-30T00:17:21.298+08:00","transaction_id":"4228ffae4b393754db8c","end":"2015-08-30T00:17:21.298+08:00","children":[],"duration":0.155},{"name":"sql.active_record","payload":{"sql":"begin transaction","name":null,"connection_id":70132700731080,"statement_name":null,"binds":[],"line":30,"filename":"/Users/mikechen/oracle/jointest/app/controllers/orders_controller.rb","method":"checkout_allpay"},"time":"2015-08-30T00:17:21.306+08:00","transaction_id":"4228ffae4b393754db8c","end":"2015-08-30T00:17:21.307+08:00","children":[],"duration":0.5770000000000001},{"name":"sql.active_record","payload":{"sql":"INSERT INTO \"payments\" (\"order_id\", \"payment_method\", \"created_at\", \"updated_at\") VALUES (?, ?, ?, ?)","name":"SQL","connection_id":70132700731080,"statement_name":null,"binds":[[{"name":"order_id","cast_type":{"precision":null,"scale":null,"limit":4,"range":"-2147483648...2147483648"},"sql_type":"integer(4)","null":true,"default":null,"default_function":null},25],[{"name":"payment_method","cast_type":{"precision":null,"scale":null,"limit":255},"sql_type":"varchar(255)","null":true,"default":null,"default_function":null},"Credit"],[{"name":"created_at","cast_type":{"precision":null,"scale":null,"limit":null},"sql_type":"datetime","null":false,"default":null,"default_function":null},"2015-08-29 16:17:21.309689"],[{"name":"updated_at","cast_type":{"precision":null,"scale":null,"limit":null},"sql_type":"datetime","null":false,"default":null,"default_function":null},"2015-08-29 16:17:21.309689"]],"line":30,"filename":"/Users/mikechen/oracle/jointest/app/controllers/orders_controller.rb","method":"checkout_allpay"},"time":"2015-08-30T00:17:21.312+08:00","transaction_id":"4228ffae4b393754db8c","end":"2015-08-30T00:17:21.313+08:00","children":[],"duration":1.323},{"name":"sql.active_record","payload":{"sql":"commit transaction","name":null,"connection_id":70132700731080,"statement_name":null,"binds":[],"line":30,"filename":"/Users/mikechen/oracle/jointest/app/controllers/orders_controller.rb","method":"checkout_allpay"},"time":"2015-08-30T00:17:21.316+08:00","transaction_id":"4228ffae4b393754db8c","end":"2015-08-30T00:17:21.318+08:00","children":[],"duration":1.4809999999999999},{"name":"render_template.action_view","payload":{"identifier":"/Users/mikechen/oracle/jointest/app/views/orders/checkout_allpay.html.erb","layout":null},"time":"2015-08-30T00:17:21.322+08:00","transaction_id":"2329eddd75c1b1d11b67","end":"2015-08-30T00:17:21.325+08:00","children":[],"duration":3.4650000000000003},{"name":"process_action.action_controller","payload":{"controller":"OrdersController","action":"checkout_allpay","params":{"controller":"orders","action":"checkout_allpay","id":"25"},"format":"html","method":"GET","path":"/orders/25/checkout_allpay","status":200,"view_runtime":5.645395998726599,"db_runtime":3.1780000000000004},"time":"2015-08-30T00:17:21.278+08:00","transaction_id":"2329eddd75c1b1d11b67","end":"2015-08-30T00:17:21.326+08:00","children":[],"duration":47.330999999999996}]